{"Physical Object": {"Anatomie": [["0.00021", "0.00016", "0.00003", "0.00002"]], "Arzneimittel": [["0.01860", "0.01301", "0.00167", "0.00125"]], "Chemie": [["0.05690", "0.03608", "0.00463", "0.00349"]]}, " Conceptual Entity": {"Klinisches Attribut": [["0.00000", "0.00000", "0.00000", "0.00000", "0.00000"]], "Quantitatives Konzept": [["0.00001", "0.00001", "0.00000", "0.00000", "0.00000"]], "Zeichen oder Symptom": [["0.00000", "0.00000", "0.00000", "0.00000", "0.00000", "0.00000"]], "Labor- oder Testergebnis": [["0.00014", "0.00016", "0.00016", "0.00018", "0.00009", "0.00001", "0.00000"]], "Zeitliches Konzept": [["0.00000", "0.00000", "0.00000", "0.00000", "0.00000"]]}, "Activity": {"Laborverfahren": [["0.00000", "0.00000", "0.00000", "0.00000"]], "Diagnostisches Verfahren": [["0.00000", "0.00000", "0.00000", "0.00000", "0.00000"]], "Therapeutisches oder praeventives Verfahren": [["0.00030", "0.00030", "0.00035", "0.00032", "0.00013", "0.00002", "0.00001"]]}, "Phenomenon or Process": {"Verletzung oder Vergiftung": [["0.00000", "0.00000", "0.00000", "0.00000", "0.00000", "0.00000"]], "Physiologische Funktion": [["0.99989", "0.99989", "0.00265", "0.99988", "0.99984"]], "Pathologische Funktion": [["0.00002", "0.00002", "0.00000", "0.00001", "0.00001"]], "Krankheit": [["0.00778", "0.00080", "0.00026", "0.00019"]], "Psychische oder Verhaltensstoerung": [["0.00002", "0.00001", "0.00002", "0.00000", "0.00000", "0.00000"]]}, "Health State": {"Gesunder Zustand": [["0.99954", "0.99962", "0.99901", "0.00120", "0.00049"]], "Verschlechter Zustand": [["0.28731", "0.30754", "0.25574", "0.00161", "0.00028"]]}, "Factuality": {"kein oder negiert": [["0.00000", "0.00000", "0.00000", "0.00000", "0.00000", "0.00000"]], "gering": [["0.76154", "0.51087", "0.00852", "0.00383"]], "fraglich": [["0.59233", "0.40046", "0.02020", "0.01171"]], "zukueftig": [["0.98598", "0.92803", "0.00380", "0.00373"]], "unwahrscheinlich": [["0.43751", "0.30215", "0.00645", "0.00325"]]}, "Zeitliche Information": {"aktuelles Ereignis": [["0.00001", "0.00001", "0.00001", "0.00000", "0.00000"]], "Vergangenheit zum aktuellen Ereignis": [["0.00001", "0.00000", "0.00000", "0.00001", "0.00000", "0.00000", "0.00000"]], "vergangenes Ereignis": [["0.00000", "0.00000", "0.00000", "0.00000", "0.00000"]], "zukuenftiges Ereignis": [["0.00105", "0.00130", "0.00056", "0.00002", "0.00002"]]}}