{"Physical Object": {"0.5": [[["Tx", "0", "O"], ["vor", "0", "O"], ["4", "0", "O"], ["Wochen", "0", "O"], [",", "0", "O"], ["Krea", "0", "O"], ["pr\u00e4", "0", "O"], ["Tx", "0", "O"], ["4", "0", "O"], [",", "0", "O"], ["6", "0", "O"], ["jetzt", "0", "O"], ["stabilisiert", "0", "O"], ["bei", "0", "O"], ["1", "0", "O"], [",", "0", "O"], ["5", "0", "O"], ["mg", "0", "O"], ["/", "0", "O"], ["dl", "0", "O"]]], "0.6": [[["Tx", "0", "O"], ["vor", "0", "O"], ["4", "0", "O"], ["Wochen", "0", "O"], [",", "0", "O"], ["Krea", "0", "O"], ["pr\u00e4", "0", "O"], ["Tx", "0", "O"], ["4", "0", "O"], [",", "0", "O"], ["6", "0", "O"], ["jetzt", "0", "O"], ["stabilisiert", "0", "O"], ["bei", "0", "O"], ["1", "0", "O"], [",", "0", "O"], ["5", "0", "O"], ["mg", "0", "O"], ["/", "0", "O"], ["dl", "0", "O"]]], "0.7": [[["Tx", "0", "O"], ["vor", "0", "O"], ["4", "0", "O"], ["Wochen", "0", "O"], [",", "0", "O"], ["Krea", "0", "O"], ["pr\u00e4", "0", "O"], ["Tx", "0", "O"], ["4", "0", "O"], [",", "0", "O"], ["6", "0", "O"], ["jetzt", "0", "O"], ["stabilisiert", "0", "O"], ["bei", "0", "O"], ["1", "0", "O"], [",", "0", "O"], ["5", "0", "O"], ["mg", "0", "O"], ["/", "0", "O"], ["dl", "0", "O"]]], "0.8": [[["Tx", "0", "O"], ["vor", "0", "O"], ["4", "0", "O"], ["Wochen", "0", "O"], [",", "0", "O"], ["Krea", "0", "O"], ["pr\u00e4", "0", "O"], ["Tx", "0", "O"], ["4", "0", "O"], [",", "0", "O"], ["6", "0", "O"], ["jetzt", "0", "O"], ["stabilisiert", "0", "O"], ["bei", "0", "O"], ["1", "0", "O"], [",", "0", "O"], ["5", "0", "O"], ["mg", "0", "O"], ["/", "0", "O"], ["dl", "0", "O"]]]}, " Conceptual Entity": {"0.5": [[["Tx", "0", "O"], ["vor", "0", "O"], ["4", "5", "T079"], ["Wochen", "5", "T079"], [",", "0", "O"], ["Krea", "1", "T201"], ["pr\u00e4", "0", "O"], ["Tx", "0", "O"], ["4", "2", "T081"], [",", "2", "T081"], ["6", "2", "T081"], ["jetzt", "0", "O"], ["stabilisiert", "0", "O"], ["bei", "0", "O"], ["1", "2", "T081"], [",", "2", "T081"], ["5", "2", "T081"], ["mg", "2", "T081"], ["/", "2", "T081"], ["dl", "2", "T081"]]], "0.6": [[["Tx", "0", "O"], ["vor", "0", "O"], ["4", "5", "T079"], ["Wochen", "5", "T079"], [",", "0", "O"], ["Krea", "1", "T201"], ["pr\u00e4", "0", "O"], ["Tx", "0", "O"], ["4", "2", "T081"], [",", "2", "T081"], ["6", "2", "T081"], ["jetzt", "0", "O"], ["stabilisiert", "0", "O"], ["bei", "0", "O"], ["1", "2", "T081"], [",", "2", "T081"], ["5", "2", "T081"], ["mg", "2", "T081"], ["/", "2", "T081"], ["dl", "2", "T081"]]], "0.7": [[["Tx", "0", "O"], ["vor", "0", "O"], ["4", "0", "O"], ["Wochen", "0", "O"], [",", "0", "O"], ["Krea", "1", "T201"], ["pr\u00e4", "0", "O"], ["Tx", "0", "O"], ["4", "2", "T081"], [",", "2", "T081"], ["6", "2", "T081"], ["jetzt", "0", "O"], ["stabilisiert", "0", "O"], ["bei", "0", "O"], ["1", "2", "T081"], [",", "2", "T081"], ["5", "2", "T081"], ["mg", "2", "T081"], ["/", "2", "T081"], ["dl", "2", "T081"]]], "0.8": [[["Tx", "0", "O"], ["vor", "0", "O"], ["4", "0", "O"], ["Wochen", "0", "O"], [",", "0", "O"], ["Krea", "1", "T201"], ["pr\u00e4", "0", "O"], ["Tx", "0", "O"], ["4", "2", "T081"], [",", "2", "T081"], ["6", "2", "T081"], ["jetzt", "0", "O"], ["stabilisiert", "0", "O"], ["bei", "0", "O"], ["1", "2", "T081"], [",", "2", "T081"], ["5", "2", "T081"], ["mg", "2", "T081"], ["/", "2", "T081"], ["dl", "2", "T081"]]]}, "Activity": {"0.5": [[["Tx", "0", "O"], ["vor", "0", "O"], ["4", "0", "O"], ["Wochen", "0", "O"], [",", "0", "O"], ["Krea", "0", "O"], ["pr\u00e4", "0", "O"], ["Tx", "0", "O"], ["4", "0", "O"], [",", "0", "O"], ["6", "0", "O"], ["jetzt", "0", "O"], ["stabilisiert", "0", "O"], ["bei", "0", "O"], ["1", "0", "O"], [",", "0", "O"], ["5", "0", "O"], ["mg", "0", "O"], ["/", "0", "O"], ["dl", "0", "O"]]], "0.6": [[["Tx", "0", "O"], ["vor", "0", "O"], ["4", "0", "O"], ["Wochen", "0", "O"], [",", "0", "O"], ["Krea", "0", "O"], ["pr\u00e4", "0", "O"], ["Tx", "0", "O"], ["4", "0", "O"], [",", "0", "O"], ["6", "0", "O"], ["jetzt", "0", "O"], ["stabilisiert", "0", "O"], ["bei", "0", "O"], ["1", "0", "O"], [",", "0", "O"], ["5", "0", "O"], ["mg", "0", "O"], ["/", "0", "O"], ["dl", "0", "O"]]], "0.7": [[["Tx", "0", "O"], ["vor", "0", "O"], ["4", "0", "O"], ["Wochen", "0", "O"], [",", "0", "O"], ["Krea", "0", "O"], ["pr\u00e4", "0", "O"], ["Tx", "0", "O"], ["4", "0", "O"], [",", "0", "O"], ["6", "0", "O"], ["jetzt", "0", "O"], ["stabilisiert", "0", "O"], ["bei", "0", "O"], ["1", "0", "O"], [",", "0", "O"], ["5", "0", "O"], ["mg", "0", "O"], ["/", "0", "O"], ["dl", "0", "O"]]], "0.8": [[["Tx", "0", "O"], ["vor", "0", "O"], ["4", "0", "O"], ["Wochen", "0", "O"], [",", "0", "O"], ["Krea", "0", "O"], ["pr\u00e4", "0", "O"], ["Tx", "0", "O"], ["4", "0", "O"], [",", "0", "O"], ["6", "0", "O"], ["jetzt", "0", "O"], ["stabilisiert", "0", "O"], ["bei", "0", "O"], ["1", "0", "O"], [",", "0", "O"], ["5", "0", "O"], ["mg", "0", "O"], ["/", "0", "O"], ["dl", "0", "O"]]]}, "Phenomenon or Process": {"0.5": [[["Tx", "0", "O"], ["vor", "0", "O"], ["4", "0", "O"], ["Wochen", "0", "O"], [",", "0", "O"], ["Krea", "0", "O"], ["pr\u00e4", "0", "O"], ["Tx", "0", "O"], ["4", "0", "O"], [",", "0", "O"], ["6", "0", "O"], ["jetzt", "0", "O"], ["stabilisiert", "0", "O"], ["bei", "0", "O"], ["1", "0", "O"], [",", "0", "O"], ["5", "0", "O"], ["mg", "0", "O"], ["/", "0", "O"], ["dl", "0", "O"]]], "0.6": [[["Tx", "0", "O"], ["vor", "0", "O"], ["4", "0", "O"], ["Wochen", "0", "O"], [",", "0", "O"], ["Krea", "0", "O"], ["pr\u00e4", "0", "O"], ["Tx", "0", "O"], ["4", "0", "O"], [",", "0", "O"], ["6", "0", "O"], ["jetzt", "0", "O"], ["stabilisiert", "0", "O"], ["bei", "0", "O"], ["1", "0", "O"], [",", "0", "O"], ["5", "0", "O"], ["mg", "0", "O"], ["/", "0", "O"], ["dl", "0", "O"]]], "0.7": [[["Tx", "0", "O"], ["vor", "0", "O"], ["4", "0", "O"], ["Wochen", "0", "O"], [",", "0", "O"], ["Krea", "0", "O"], ["pr\u00e4", "0", "O"], ["Tx", "0", "O"], ["4", "0", "O"], [",", "0", "O"], ["6", "0", "O"], ["jetzt", "0", "O"], ["stabilisiert", "0", "O"], ["bei", "0", "O"], ["1", "0", "O"], [",", "0", "O"], ["5", "0", "O"], ["mg", "0", "O"], ["/", "0", "O"], ["dl", "0", "O"]]], "0.8": [[["Tx", "0", "O"], ["vor", "0", "O"], ["4", "0", "O"], ["Wochen", "0", "O"], [",", "0", "O"], ["Krea", "0", "O"], ["pr\u00e4", "0", "O"], ["Tx", "0", "O"], ["4", "0", "O"], [",", "0", "O"], ["6", "0", "O"], ["jetzt", "0", "O"], ["stabilisiert", "0", "O"], ["bei", "0", "O"], ["1", "0", "O"], [",", "0", "O"], ["5", "0", "O"], ["mg", "0", "O"], ["/", "0", "O"], ["dl", "0", "O"]]]}, "Health State": {"0.5": [[["Tx", "0", "O"], ["vor", "0", "O"], ["4", "0", "O"], ["Wochen", "0", "O"], [",", "0", "O"], ["Krea", "0", "O"], ["pr\u00e4", "0", "O"], ["Tx", "0", "O"], ["4", "0", "O"], [",", "0", "O"], ["6", "0", "O"], ["jetzt", "0", "O"], ["stabilisiert", "1", "T300"], ["bei", "0", "O"], ["1", "0", "O"], [",", "0", "O"], ["5", "0", "O"], ["mg", "0", "O"], ["/", "0", "O"], ["dl", "0", "O"]]], "0.6": [[["Tx", "0", "O"], ["vor", "0", "O"], ["4", "0", "O"], ["Wochen", "0", "O"], [",", "0", "O"], ["Krea", "0", "O"], ["pr\u00e4", "0", "O"], ["Tx", "0", "O"], ["4", "0", "O"], [",", "0", "O"], ["6", "0", "O"], ["jetzt", "0", "O"], ["stabilisiert", "1", "T300"], ["bei", "0", "O"], ["1", "0", "O"], [",", "0", "O"], ["5", "0", "O"], ["mg", "0", "O"], ["/", "0", "O"], ["dl", "0", "O"]]], "0.7": [[["Tx", "0", "O"], ["vor", "0", "O"], ["4", "0", "O"], ["Wochen", "0", "O"], [",", "0", "O"], ["Krea", "0", "O"], ["pr\u00e4", "0", "O"], ["Tx", "0", "O"], ["4", "0", "O"], [",", "0", "O"], ["6", "0", "O"], ["jetzt", "0", "O"], ["stabilisiert", "1", "T300"], ["bei", "0", "O"], ["1", "0", "O"], [",", "0", "O"], ["5", "0", "O"], ["mg", "0", "O"], ["/", "0", "O"], ["dl", "0", "O"]]], "0.8": [[["Tx", "0", "O"], ["vor", "0", "O"], ["4", "0", "O"], ["Wochen", "0", "O"], [",", "0", "O"], ["Krea", "0", "O"], ["pr\u00e4", "0", "O"], ["Tx", "0", "O"], ["4", "0", "O"], [",", "0", "O"], ["6", "0", "O"], ["jetzt", "0", "O"], ["stabilisiert", "1", "T300"], ["bei", "0", "O"], ["1", "0", "O"], [",", "0", "O"], ["5", "0", "O"], ["mg", "0", "O"], ["/", "0", "O"], ["dl", "0", "O"]]]}, "Factuality": {"0.5": [[["Tx", "0", "O"], ["vor", "0", "O"], ["4", "0", "O"], ["Wochen", "0", "O"], [",", "0", "O"], ["Krea", "0", "O"], ["pr\u00e4", "0", "O"], ["Tx", "0", "O"], ["4", "0", "O"], [",", "0", "O"], ["6", "0", "O"], ["jetzt", "0", "O"], ["stabilisiert", "0", "O"], ["bei", "0", "O"], ["1", "0", "O"], [",", "0", "O"], ["5", "0", "O"], ["mg", "0", "O"], ["/", "0", "O"], ["dl", "0", "O"]]], "0.6": [[["Tx", "0", "O"], ["vor", "0", "O"], ["4", "0", "O"], ["Wochen", "0", "O"], [",", "0", "O"], ["Krea", "0", "O"], ["pr\u00e4", "0", "O"], ["Tx", "0", "O"], ["4", "0", "O"], [",", "0", "O"], ["6", "0", "O"], ["jetzt", "0", "O"], ["stabilisiert", "0", "O"], ["bei", "0", "O"], ["1", "0", "O"], [",", "0", "O"], ["5", "0", "O"], ["mg", "0", "O"], ["/", "0", "O"], ["dl", "0", "O"]]], "0.7": [[["Tx", "0", "O"], ["vor", "0", "O"], ["4", "0", "O"], ["Wochen", "0", "O"], [",", "0", "O"], ["Krea", "0", "O"], ["pr\u00e4", "0", "O"], ["Tx", "0", "O"], ["4", "0", "O"], [",", "0", "O"], ["6", "0", "O"], ["jetzt", "0", "O"], ["stabilisiert", "0", "O"], ["bei", "0", "O"], ["1", "0", "O"], [",", "0", "O"], ["5", "0", "O"], ["mg", "0", "O"], ["/", "0", "O"], ["dl", "0", "O"]]], "0.8": [[["Tx", "0", "O"], ["vor", "0", "O"], ["4", "0", "O"], ["Wochen", "0", "O"], [",", "0", "O"], ["Krea", "0", "O"], ["pr\u00e4", "0", "O"], ["Tx", "0", "O"], ["4", "0", "O"], [",", "0", "O"], ["6", "0", "O"], ["jetzt", "0", "O"], ["stabilisiert", "0", "O"], ["bei", "0", "O"], ["1", "0", "O"], [",", "0", "O"], ["5", "0", "O"], ["mg", "0", "O"], ["/", "0", "O"], ["dl", "0", "O"]]]}, "Zeitliche Information": {"0.5": [[["Tx", "0", "O"], ["vor", "0", "O"], ["4", "0", "O"], ["Wochen", "0", "O"], [",", "0", "O"], ["Krea", "0", "O"], ["pr\u00e4", "0", "O"], ["Tx", "0", "O"], ["4", "0", "O"], [",", "0", "O"], ["6", "0", "O"], ["jetzt", "0", "O"], ["stabilisiert", "0", "O"], ["bei", "0", "O"], ["1", "0", "O"], [",", "0", "O"], ["5", "0", "O"], ["mg", "0", "O"], ["/", "0", "O"], ["dl", "0", "O"]]], "0.6": [[["Tx", "0", "O"], ["vor", "0", "O"], ["4", "0", "O"], ["Wochen", "0", "O"], [",", "0", "O"], ["Krea", "0", "O"], ["pr\u00e4", "0", "O"], ["Tx", "0", "O"], ["4", "0", "O"], [",", "0", "O"], ["6", "0", "O"], ["jetzt", "0", "O"], ["stabilisiert", "0", "O"], ["bei", "0", "O"], ["1", "0", "O"], [",", "0", "O"], ["5", "0", "O"], ["mg", "0", "O"], ["/", "0", "O"], ["dl", "0", "O"]]], "0.7": [[["Tx", "0", "O"], ["vor", "0", "O"], ["4", "0", "O"], ["Wochen", "0", "O"], [",", "0", "O"], ["Krea", "0", "O"], ["pr\u00e4", "0", "O"], ["Tx", "0", "O"], ["4", "0", "O"], [",", "0", "O"], ["6", "0", "O"], ["jetzt", "0", "O"], ["stabilisiert", "0", "O"], ["bei", "0", "O"], ["1", "0", "O"], [",", "0", "O"], ["5", "0", "O"], ["mg", "0", "O"], ["/", "0", "O"], ["dl", "0", "O"]]], "0.8": [[["Tx", "0", "O"], ["vor", "0", "O"], ["4", "0", "O"], ["Wochen", "0", "O"], [",", "0", "O"], ["Krea", "0", "O"], ["pr\u00e4", "0", "O"], ["Tx", "0", "O"], ["4", "0", "O"], [",", "0", "O"], ["6", "0", "O"], ["jetzt", "0", "O"], ["stabilisiert", "0", "O"], ["bei", "0", "O"], ["1", "0", "O"], [",", "0", "O"], ["5", "0", "O"], ["mg", "0", "O"], ["/", "0", "O"], ["dl", "0", "O"]]]}}